rnd_cat/__init__.py
rnd_cat/rnd_cat.py
rnd_cat-0.0.4.dist-info/METADATA
rnd_cat-0.0.4.dist-info/WHEEL
rnd_cat-0.0.4.dist-info/RECORD
