Metadata-Version: 2.1
Name: rnd-cat
Version: 0.0.4
Summary: A simple python module for receiving random images with cats.
Author: Almas Vildanov
Author-email: almasvildanov@gmail.com
Requires-Python: >=3.9,<4.0
Classifier: Programming Language :: Python :: 3
Classifier: Programming Language :: Python :: 3.9
Classifier: Programming Language :: Python :: 3.10
Classifier: Programming Language :: Python :: 3.11
Classifier: Programming Language :: Python :: 3.12
Requires-Dist: requests (>=2.32.3,<3.0.0)
